twcli/__init__.py
twcli/__main__.py
twcli/run.html
twcli/run.py
twcli/scaffolding-with-music.js
twcli/version.py
turbowarp_cli-1.1.0.dist-info/METADATA
turbowarp_cli-1.1.0.dist-info/WHEEL
turbowarp_cli-1.1.0.dist-info/entry_points.txt
turbowarp_cli-1.1.0.dist-info/top_level.txt
turbowarp_cli-1.1.0.dist-info/RECORD
