Metadata-Version: 2.4
Name: turbowarp-cli
Version: 1.1.0
Summary: Run scratch projects in your terminal using turbowarp scaffolding
Author: faretek1
Project-URL: Source, https://github.com/inflated-goboscript/tw-cli
Project-URL: Documentation, https://inflated-goboscript.github.io/tw-cli/
Project-URL: Homepage, https://inflated-goboscript.github.io/
Keywords: goboscript,scratch,turbowarp
Requires-Dist: playwright~=1.55.0
Requires-Dist: rich~=14.1.0
Dynamic: author
Dynamic: description
Dynamic: description-content-type
Dynamic: keywords
Dynamic: project-url
Dynamic: requires-dist
Dynamic: summary
